brassy/__init__.py
brassy/actions/build_release_notes.py
brassy/actions/init.py
brassy/actions/prune_yaml.py
brassy/brassy.py
brassy/templates/release_yaml_template.py
brassy/templates/settings_template.py
brassy/utils/CLI.py
brassy/utils/file_handler.py
brassy/utils/git_handler.py
brassy/utils/messages.py
brassy/utils/settings_manager.py
brassy-0.0.3.dist-info/LICENSE
brassy-0.0.3.dist-info/METADATA
brassy-0.0.3.dist-info/WHEEL
brassy-0.0.3.dist-info/entry_points.txt
brassy-0.0.3.dist-info/RECORD
